{"lista":{"cabecera":{"dato":{"@class":"Modelo.Vehiculo","id":0,"marca":{"marca":"Chevrolet","tipoVehiculo":"Auto"},"matricula":"LCL-561","precio":13.5,"color":"Negro","disponibles":1},"siguiente":{"dato":{"@class":"Modelo.Vehiculo","id":1,"marca":{"marca":"Chevrolet","tipoVehiculo":"Auto"},"matricula":"LCL-561","precio":13.5,"color":"Rojo","disponibles":31},"siguiente":{"dato":{"@class":"Modelo.Vehiculo","id":2,"marca":{"marca":"Nissan","tipoVehiculo":"Auto"},"matricula":"LBA-7458","precio":12,"color":"Azul","disponibles":3}}}},"size":3}}